fastmcp_pdftools/__init__.py
fastmcp_pdftools/server.py
fastmcp_pdftools-0.1.3.dist-info/METADATA
fastmcp_pdftools-0.1.3.dist-info/WHEEL
fastmcp_pdftools-0.1.3.dist-info/entry_points.txt
fastmcp_pdftools-0.1.3.dist-info/licenses/LICENSE
fastmcp_pdftools-0.1.3.dist-info/RECORD
