Metadata-Version: 2.4
Name: fastmcp-pdftools
Version: 0.1.3
Summary: MCP PDF reader server allowing to read  PDF files
Author-email: Ola Tarkowska <ola@entrypoint.tech>
License-File: LICENSE
Classifier: Intended Audience :: Developers
Classifier: Programming Language :: Python :: 3
Classifier: Programming Language :: Python :: 3.10
Classifier: Programming Language :: Python :: 3.11
Classifier: Programming Language :: Python :: 3.12
Requires-Python: >=3.10
Requires-Dist: fastmcp>=2.0.0
Requires-Dist: pypdf>=6.0.0
Provides-Extra: dev
Requires-Dist: pytest-asyncio>=0.21.0; extra == 'dev'
Requires-Dist: pytest-cov>=4.1.0; extra == 'dev'
Requires-Dist: pytest>=7.4.0; extra == 'dev'
Requires-Dist: reportlab>=4.0.0; extra == 'dev'
